convergaince_client/__init__.py
convergaince_client/cfg.py
convergaince_client/dataset.py
convergaince_client/lib.py
convergaince_client/main.py
convergaince_client/retrieve.py
convergaince_client-0.0.1.dist-info/METADATA
convergaince_client-0.0.1.dist-info/WHEEL
convergaince_client-0.0.1.dist-info/top_level.txt
convergaince_client-0.0.1.dist-info/RECORD
